mada_holidays/__init__.py
mada_holidays/core.py
tests/__init__.py
tests/test_core.py
mada_holidays-1.0.dist-info/METADATA
mada_holidays-1.0.dist-info/WHEEL
mada_holidays-1.0.dist-info/top_level.txt
mada_holidays-1.0.dist-info/RECORD
